omito_config_core/__init__.py
omito_config_core/base_plugin.py
omito_config_core/load_config.py
omito_config_core-0.1.10.dist-info/WHEEL
omito_config_core-0.1.10.dist-info/METADATA
omito_config_core-0.1.10.dist-info/RECORD
